hello_ci/__init__.py
hello_ci/hello/__init__.py
hello_ci/hello/hello.py
hello_ci/world/__init__.py
hello_ci/world/world.py
hello_ci-1.0.0.dist-info/METADATA
hello_ci-1.0.0.dist-info/WHEEL
hello_ci-1.0.0.dist-info/RECORD
