Metadata-Version: 2.1
Name: hello-ci
Version: 1.0.0
Summary: A test example of a package 
License: MIT
Author: asdftoger
Requires-Python: >=3.8,<4.0
Classifier: License :: OSI Approved :: MIT License
Classifier: Programming Language :: Python :: 3
Classifier: Programming Language :: Python :: 3.8
Classifier: Programming Language :: Python :: 3.9
Classifier: Programming Language :: Python :: 3.10
Classifier: Programming Language :: Python :: 3.11
Requires-Dist: numpy
Requires-Dist: pandas
Project-URL: Documentation, https://github.com/asdftoger/hello_ci
